{"type":"FeatureCollection","features":[{"type":"Feature","geometry":{"type":"Point","coordinates":[-122.98496239995545,49.129365421301046]},"properties":{"Name":"Burns Bog 1","Info":"https://ubc-micromet.github.io/Data.html#burns-bog-1"}}]}