{"type":"FeatureCollection","features":[{"type":"Feature","id":7,"geometry":{"type":"Point","coordinates":[-122.99408,49.13806]},"properties":{"OBJECTID":8,"Name":"BBS","Longitude":122.99408,"Latitude":49.13806,"Access":"Enter Burns Bog at 80th Street, park in the parking lot and head east, following the trails with the blue and orange flags to reach the site.","WebPlot":"","Start":2021,"Description":"A Pine-Sphagnum-Woodland in th 2016 Burn Zone."}}]}